cogworks/__init__.py
cogworks/component.py
cogworks/engine.py
cogworks/game_object.py
cogworks/scene_manager.py
cogworks/trigger_collision_manager.py
cogworks/components/__init__.py
cogworks/components/audio_listener.py
cogworks/components/audio_source.py
cogworks/components/background.py
cogworks/components/camera.py
cogworks/components/linerenderer.py
cogworks/components/particle.py
cogworks/components/particle_effect.py
cogworks/components/rigidbody2d.py
cogworks/components/script_component.py
cogworks/components/sprite.py
cogworks/components/sprite_animation.py
cogworks/components/transform.py
cogworks/components/trigger_collider.py
cogworks/components/ui/__init__.py
cogworks/components/ui/ui_button.py
cogworks/components/ui/ui_fill_image.py
cogworks/components/ui/ui_image.py
cogworks/components/ui/ui_label.py
cogworks/components/ui/ui_layout.py
cogworks/components/ui/ui_renderer.py
cogworks/components/ui/ui_transform.py
cogworks/engine_assets/__init__.py
cogworks/engine_assets/__pycache__/__init__.cpython-312.pyc
cogworks/engine_assets/images/cog_works_icon.png
cogworks/engine_assets/images/cog_works_icon_2.png
cogworks/exceptions/__init__.py
cogworks/exceptions/missing_component_error.py
cogworks/pygame_wrappers/__init__.py
cogworks/pygame_wrappers/event_manager.py
cogworks/pygame_wrappers/input_manager.py
cogworks/pygame_wrappers/window.py
cogworks/utils/__init__.py
cogworks/utils/asset_loader.py
cogworks-0.2.14.dist-info/METADATA
cogworks-0.2.14.dist-info/WHEEL
cogworks-0.2.14.dist-info/top_level.txt
cogworks-0.2.14.dist-info/RECORD
