Metadata-Version: 2.4
Name: cogworks
Version: 0.2.14
Summary: 2D Python game engine built on pygame and pymunk
Home-page: https://github.com/Dempsey845/cog-works-engine
Author: Dempsey Newton
Author-email: Dempsey Newton <dempseynewton1@gmail.com>
License: MIT
Requires-Python: >=3.12
Requires-Dist: pygame>=2.6.1
Requires-Dist: pymunk>=7.1.0
